vectrixdb/__init__.py
vectrixdb/cli.py
vectrixdb/easy.py
vectrixdb/api/__init__.py
vectrixdb/api/server.py
vectrixdb/benchmarks/__init__.py
vectrixdb/benchmarks/datasets.py
vectrixdb/benchmarks/metrics.py
vectrixdb/benchmarks/reports.py
vectrixdb/benchmarks/runner.py
vectrixdb/core/__init__.py
vectrixdb/core/advanced_search.py
vectrixdb/core/cache.py
vectrixdb/core/collection.py
vectrixdb/core/database.py
vectrixdb/core/neural_search.py
vectrixdb/core/scaling.py
vectrixdb/core/sparse_index.py
vectrixdb/core/storage.py
vectrixdb/core/types.py
vectrixdb/core/batch/__init__.py
vectrixdb/core/batch/memory.py
vectrixdb/core/batch/parallel.py
vectrixdb/core/batch/streaming.py
vectrixdb/core/graphrag/__init__.py
vectrixdb/core/graphrag/chunker.py
vectrixdb/core/graphrag/config.py
vectrixdb/core/graphrag/pipeline.py
vectrixdb/core/graphrag/summarizer.py
vectrixdb/core/graphrag/extractor/__init__.py
vectrixdb/core/graphrag/extractor/base.py
vectrixdb/core/graphrag/extractor/hybrid_extractor.py
vectrixdb/core/graphrag/extractor/llm_extractor.py
vectrixdb/core/graphrag/extractor/nlp_extractor.py
vectrixdb/core/graphrag/extractor/rebel_extractor.py
vectrixdb/core/graphrag/graph/__init__.py
vectrixdb/core/graphrag/graph/community.py
vectrixdb/core/graphrag/graph/knowledge_graph.py
vectrixdb/core/graphrag/graph/storage.py
vectrixdb/core/graphrag/retriever/__init__.py
vectrixdb/core/graphrag/retriever/global_search.py
vectrixdb/core/graphrag/retriever/hybrid_search.py
vectrixdb/core/graphrag/retriever/local_search.py
vectrixdb/core/hnsw/__init__.py
vectrixdb/core/hnsw/distance.py
vectrixdb/core/hnsw/index.py
vectrixdb/core/payload_index/__init__.py
vectrixdb/core/payload_index/base.py
vectrixdb/core/payload_index/geo.py
vectrixdb/core/payload_index/manager.py
vectrixdb/core/payload_index/numeric.py
vectrixdb/core/payload_index/string.py
vectrixdb/core/payload_index/tag.py
vectrixdb/core/quantization/__init__.py
vectrixdb/core/quantization/base.py
vectrixdb-1.0.0.dist-info/METADATA
vectrixdb-1.0.0.dist-info/WHEEL
vectrixdb-1.0.0.dist-info/entry_points.txt
vectrixdb-1.0.0.dist-info/licenses/LICENSE
vectrixdb-1.0.0.dist-info/RECORD
