Metadata-Version: 2.4
Name: vectrixdb
Version: 1.0.0
Summary: Where vectors come alive - A lightweight, visual-first vector database with embedded ML models
Project-URL: Homepage, https://github.com/knowusuboaky/VectrixDB
Project-URL: Documentation, https://github.com/knowusuboaky/VectrixDB#readme
Project-URL: Repository, https://github.com/knowusuboaky/VectrixDB
Author-email: Kwadwo Daddy Nyame Owusu - Boakye <kwadwo.owusuboakye@outlook.com>
License-Expression: Apache-2.0
License-File: LICENSE
Keywords: ai,approximate-nearest-neighbors,embeddings,hnsw,machine-learning,similarity-search,vector-database
Classifier: Development Status :: 5 - Production/Stable
Classifier: Intended Audience :: Developers
Classifier: License :: OSI Approved :: Apache Software License
Classifier: Programming Language :: Python :: 3
Classifier: Programming Language :: Python :: 3.9
Classifier: Programming Language :: Python :: 3.10
Classifier: Programming Language :: Python :: 3.11
Classifier: Programming Language :: Python :: 3.12
Classifier: Programming Language :: Python :: 3.13
Classifier: Topic :: Database
Classifier: Topic :: Scientific/Engineering :: Artificial Intelligence
Requires-Python: >=3.9
Requires-Dist: aiosqlite>=0.19.0
Requires-Dist: fastapi>=0.109.0
Requires-Dist: httpx>=0.26.0
Requires-Dist: numpy>=1.24.0
Requires-Dist: onnxruntime>=1.15.0
Requires-Dist: orjson>=3.9.0
Requires-Dist: pydantic>=2.0.0
Requires-Dist: rich>=13.0.0
Requires-Dist: tokenizers>=0.15.0
Requires-Dist: typer>=0.9.0
Requires-Dist: usearch>=2.0.0
Requires-Dist: uvicorn[standard]>=0.27.0
Requires-Dist: websockets>=12.0
Provides-Extra: all
Requires-Dist: black>=23.0.0; extra == 'all'
Requires-Dist: fastembed>=0.2.0; extra == 'all'
Requires-Dist: mypy>=1.0.0; extra == 'all'
Requires-Dist: pytest-asyncio>=0.23.0; extra == 'all'
Requires-Dist: pytest-cov>=4.0.0; extra == 'all'
Requires-Dist: pytest>=7.0.0; extra == 'all'
Requires-Dist: ruff>=0.1.0; extra == 'all'
Requires-Dist: scikit-learn>=1.3.0; extra == 'all'
Requires-Dist: sentence-transformers>=2.2.0; extra == 'all'
Requires-Dist: umap-learn>=0.5.0; extra == 'all'
Provides-Extra: dev
Requires-Dist: black>=23.0.0; extra == 'dev'
Requires-Dist: mypy>=1.0.0; extra == 'dev'
Requires-Dist: pytest-asyncio>=0.23.0; extra == 'dev'
Requires-Dist: pytest-cov>=4.0.0; extra == 'dev'
Requires-Dist: pytest>=7.0.0; extra == 'dev'
Requires-Dist: ruff>=0.1.0; extra == 'dev'
Provides-Extra: embeddings
Requires-Dist: fastembed>=0.2.0; extra == 'embeddings'
Requires-Dist: sentence-transformers>=2.2.0; extra == 'embeddings'
Provides-Extra: fastembed
Requires-Dist: fastembed>=0.2.0; extra == 'fastembed'
Provides-Extra: hf
Requires-Dist: sentence-transformers>=2.2.0; extra == 'hf'
Provides-Extra: setup-models
Requires-Dist: optimum[onnxruntime]>=1.12.0; extra == 'setup-models'
Requires-Dist: torch>=2.0.0; extra == 'setup-models'
Requires-Dist: transformers>=4.30.0; extra == 'setup-models'
Provides-Extra: viz
Requires-Dist: scikit-learn>=1.3.0; extra == 'viz'
Requires-Dist: umap-learn>=0.5.0; extra == 'viz'
